<?xml version="1.0" encoding="utf-8" ?>
<resources>
	<style name="MainTheme" parent="MainTheme.Base" >
		<item name="colorPrimary">#2196F3</item>
		<item name="colorPrimaryDark">#5d0060</item>
		<item name="colorAccent">#7f017e</item>
		<item name="android:datePickerDialogTheme">@style/AppCompatDialogStyle</item>
	</style>

	<style name="Theme.AppCompat.DayNight" parent="Theme.AppCompat.Light">
		<item name="colorAccent">#7f017e</item>
	</style>

	<style name="AppCompatDialogStyle" parent="Theme.AppCompat.Light.Dialog">
		<item name="colorAccent">#7f017e</item>
	</style>
</resources>